balboniprint/__init__.py
balboniprint-0.1.2.dist-info/METADATA
balboniprint-0.1.2.dist-info/WHEEL
balboniprint-0.1.2.dist-info/top_level.txt
balboniprint-0.1.2.dist-info/RECORD
